foliant/preprocessors/superlinks/__init__.py
foliant/preprocessors/superlinks/anchors_generator.py
foliant/preprocessors/superlinks/confluence.py
foliant/preprocessors/superlinks/superlinks.py
foliantcontrib.superlinks-1.0.12.dist-info/LICENSE
foliantcontrib.superlinks-1.0.12.dist-info/METADATA
foliantcontrib.superlinks-1.0.12.dist-info/WHEEL
foliantcontrib.superlinks-1.0.12.dist-info/top_level.txt
foliantcontrib.superlinks-1.0.12.dist-info/RECORD
