Metadata-Version: 2.1
Name: foliantcontrib.superlinks
Version: 1.0.12
Summary: Links to headings with extra magic
Home-page: UNKNOWN
Author: Daniil Minukhin
Author-email: ddddsa@gmail.com
License: MIT
Platform: any
Classifier: Development Status :: 5 - Production/Stable
Classifier: Environment :: Console
Classifier: Intended Audience :: Developers
Classifier: License :: OSI Approved :: MIT License
Classifier: Operating System :: OS Independent
Classifier: Programming Language :: Python
Classifier: Topic :: Documentation
Classifier: Topic :: Utilities
License-File: LICENSE
Requires-Dist: foliant (>=1.0.8)
Requires-Dist: foliantcontrib.meta (>=1.3.0)
Requires-Dist: foliantcontrib.anchors (>=1.0.4)
Requires-Dist: foliantcontrib.utils (>=1.0.2)
